readme_examples.py
fitxf/FitxfUnitTest.py
fitxf/__init__.py
fitxf/math/algo/encoding/Base64.py
fitxf/math/data/ut/LabelTextEmbed01.py
fitxf/math/datasource/Csv.py
fitxf/math/datasource/Datastore.py
fitxf/math/datasource/DatastoreInterface.py
fitxf/math/datasource/DbLang.py
fitxf/math/datasource/vecdb/metadata/MetadataInterface.py
fitxf/math/datasource/vecdb/model/ModelDbInterface.py
fitxf/math/datasource/vecdb/model/ModelEncoderInterface.py
fitxf/math/datasource/vecdb/model/ModelFitXForm.py
fitxf/math/datasource/vecdb/model/ModelInterface.py
fitxf/math/demo/dft.py
fitxf/math/dsp/Dft.py
fitxf/math/dsp/DspFilter.py
fitxf/math/dsp/Mdct.py
fitxf/math/fit/arc/ClassifierArc.py
fitxf/math/fit/arc/ClassifierArcInterface.py
fitxf/math/fit/arc/ClassifierArcRf.py
fitxf/math/fit/arc/ClassifierArcUnitTest.py
fitxf/math/fit/cluster/Cluster.py
fitxf/math/fit/cluster/ClusterCosine.py
fitxf/math/fit/cluster/ClusterCosineUT.py
fitxf/math/fit/cluster/ClusterUnitTest.py
fitxf/math/fit/cluster/Metrics.py
fitxf/math/fit/reg/Regression.py
fitxf/math/fit/transform/FitXformCluster.py
fitxf/math/fit/transform/FitXformInterface.py
fitxf/math/fit/transform/FitXformPca.py
fitxf/math/fit/transform/FitXformUnitTest.py
fitxf/math/fit/utils/FitUtils.py
fitxf/math/fit/utils/FitUtilsUnitTest.py
fitxf/math/fit/utils/MathUtils.py
fitxf/math/fit/utils/PatternSearch.py
fitxf/math/fit/utils/PatternSearchUnitTest.py
fitxf/math/fit/utils/TensorUtils.py
fitxf/math/function/FunctionInterface.py
fitxf/math/graph/GraphUtils.py
fitxf/math/graph/GraphUtilsUnitTest.py
fitxf/math/lang/cache/CacheTest.py
fitxf/math/lang/cache/TextSimilarityCache.py
fitxf/math/lang/encode/ImgPt.py
fitxf/math/lang/encode/LangModelInterface.py
fitxf/math/lang/encode/LangModelPt.py
fitxf/math/lang/encode/LangModelPtSingleton.py
fitxf/math/lang/measures/TextDiffCharDiff.py
fitxf/math/lang/measures/TextDiffCharFreq.py
fitxf/math/lang/measures/TextDiffInterface.py
fitxf/math/lang/measures/TextDiffSpeedTest.py
fitxf-1.2.5.dist-info/METADATA
fitxf-1.2.5.dist-info/WHEEL
fitxf-1.2.5.dist-info/top_level.txt
fitxf-1.2.5.dist-info/RECORD
